{
  "slug": "memonow",
  "createdAt": "2026-03-13",
  "name": "MemoNow",
  "category": "app",
  "platforms": ["ios"],
  "shortDescription": "ちょっとメモ。ホーム画面やロック画面のウィジェットに常時表示できる、シンプルな一枚メモアプリ。",
  "subtitle": "ちょっとメモ。ウィジェットに常時表示できる一枚メモ",
  "promoText": "「ちょっとメモ。」そんな時に、これだけでいい。ホーム画面やロック画面のウィジェットにメモを常時表示。買い物リスト、電話番号、合言葉——忘れたくない「ちょっとしたこと」を瞬時に確認できます。",
  "tags": ["日本語のみ", "iOSアプリ", "ウィジェット", "メモ"],
  "detailTags": ["日本語のみ", "iOSアプリ", "ウィジェット", "メモ"],
  "storeLinksCard": [
    {"type": "app-store", "url": "", "label": "App Store", "disabled": true}
  ],
  "storeGroupsDetail": [
    {
      "label": "ストアからダウンロード",
      "links": [
        {"type": "app-store", "url": "", "label": "App Store — 準備中", "disabled": true}
      ]
    }
  ],
  "comingSoon": true,
  "ogDescription": "ホーム画面やロック画面のウィジェットに常時表示できる、シンプルな一枚メモアプリ",
  "description": "### MemoNowについて\n\nMemoNowは、余計な機能を一切省いた「一枚メモ」アプリです。画面全体がメモ帳で、タップしてすぐ入力。書いた内容はホーム画面やロック画面のウィジェットに常時表示されるので、アプリを開かなくてもいつでも確認できます。\n\n### 主な機能\n\n- 一枚メモ — 画面全体がメモ帳。タップしてすぐに入力\n- ホーム画面ウィジェット（Small / Medium / Large）\n- ロック画面ウィジェット（Rectangular / Circular / Inline）\n- フォントサイズ調整（10pt〜48pt）\n- 背景色・文字色のカスタマイズ\n- グラデーション背景エフェクト\n- リアルタイム同期 — メモを書いた瞬間にウィジェットへ反映\n\n### 対応プラットフォーム\n\niOS 17.0以降に対応。App Storeでの公開に向けて準備中です。",
  "documents": {
    "appDisplayName": "MemoNow",
    "about": {
      "catchcopy": "「ちょっとメモ。」そんな時に、これだけでいい。",
      "subcopy": "たった一枚の、最もシンプルでわかりやすいメモアプリ。\nホーム画面ウィジェットやロック画面ウィジェットに常時表示して、瞬時に確認。タップすれば瞬時に開いて、瞬時に書き換え。\n買い物リスト、電話番号、合言葉——忘れたくない「ちょっとしたこと」を、いつでも目に留まる場所に。",
      "features": [
        {"name": "一枚メモ", "desc": "余計なものは何もない。画面全体がメモ帳。タップしてすぐ入力"},
        {"name": "ウィジェット常時表示", "desc": "メモ内容をホーム画面・ロック画面にいつでも表示。Small / Medium / Large / ロック画面対応"},
        {"name": "フォントサイズ調整", "desc": "10pt〜48ptの範囲でスライダー調整"},
        {"name": "カラーカスタマイズ", "desc": "背景色・文字色をカラーピッカーで自由に設定"},
        {"name": "グラデーション背景", "desc": "設定色に基づいた上部濃・下部淡の美しいグラデーション"},
        {"name": "リアルタイム同期", "desc": "書いた瞬間にウィジェットへ反映。アプリを閉じても即時更新"}
      ],
      "info": [
        {"key": "対応OS", "value": "iOS 17.0 以降"},
        {"key": "価格", "value": "無料"},
        {"key": "カテゴリ", "value": "仕事効率化"},
        {"key": "開発", "value": "riverapp.jp"}
      ],
      "links": [
        {"label": "プライバシーポリシー", "href": "/app-document/memonow/privacy-policy", "internal": true},
        {"label": "riverapp.jp", "href": "https://riverapp.jp", "external": true}
      ]
    },
    "contact": {
      "methods": [
        {
          "label": "お問い合わせフォーム",
          "description": "Google フォームから送信",
          "url": "https://forms.gle/68uVrDj6ACmN9PNu8",
          "external": true
        },
        {
          "label": "メールで問い合わせ",
          "description": "riverapp.jp@gmail.com",
          "url": "mailto:riverapp.jp@gmail.com",
          "external": false
        }
      ]
    },
    "privacy-policy": {
      "sections": [
        {
          "title": "はじめに",
          "body": "本プライバシーポリシーは、{appName}（以下「本アプリ」）における個人情報の取り扱いについて説明するものです。本アプリは、お客様のプライバシーを尊重し、個人情報の保護に努めます。"
        },
        {
          "title": "収集する情報",
          "body": "本アプリは、個人情報を一切収集しません。",
          "bullets": [
            "メモの内容はお使いの端末内にのみ保存され、外部サーバーへの送信は行いません",
            "フォントサイズ、背景色、文字色などの設定情報も端末内にのみ保存されます",
            "アカウント登録やログインは不要です"
          ]
        },
        {
          "title": "データの保存",
          "body": "本アプリのすべてのデータは、端末の UserDefaults（App Groups）にローカル保存されます。データはインターネットを通じて送信されることはなく、開発者がアクセスすることもできません。アプリを削除すると、すべてのデータが端末から完全に削除されます。"
        },
        {
          "title": "第三者への提供",
          "body": "本アプリは、お客様のデータを第三者に提供、販売、共有することはありません。"
        },
        {
          "title": "分析ツール・広告",
          "body": "本アプリは、分析ツールや広告 SDK を一切使用していません。"
        },
        {
          "title": "お子様のプライバシー",
          "body": "本アプリは個人情報を収集しないため、年齢を問わず安心してご利用いただけます。"
        },
        {
          "title": "プライバシーポリシーの変更",
          "body": "本プライバシーポリシーは、必要に応じて更新されることがあります。変更があった場合は、本ページにて最新の内容を掲載します。"
        },
        {
          "title": "お問い合わせ",
          "body": "本プライバシーポリシーに関するご質問やお問い合わせは、お問い合わせページよりご連絡ください。"
        }
      ],
      "lastUpdated": "2026-03-15"
    }
  }
}
